[
    {
        "createdAt": "2026-03-24T13:58:35.201Z",
        "name": "Ca 2",
        "date": "2026-03-23",
        "startTime": "09:45",
        "endTime": "13:00",
        "rowIdx": 1,
        "color": "#10b981",
        "id": "sc-1774360715201-733",
        "staffId": "4",
        "employeeId": "4",
        "staffIds": [
            "4",
            "7"
        ]
    },
    {
        "createdAt": "2026-03-24T14:01:24.703Z",
        "name": "Ca 3",
        "date": "2026-03-23",
        "startTime": "13:30",
        "endTime": "14:00",
        "rowIdx": 2,
        "color": "#f59e0b",
        "staffIds": [
            "3"
        ],
        "id": "sc-1774360884703-128"
    },
    {
        "createdAt": "2026-03-24T14:14:18.266Z",
        "name": "Ca 2",
        "date": "2026-03-24",
        "startTime": "08:00",
        "endTime": "13:00",
        "rowIdx": 1,
        "color": "#10b981",
        "staffIds": [
            "3",
            "4",
            "7"
        ],
        "id": "sc-1774361658266-215"
    },
    {
        "createdAt": "2026-03-24T14:31:43.242Z",
        "name": "Ca 3",
        "date": "2026-03-24",
        "startTime": "07:00",
        "endTime": "07:30",
        "rowIdx": 2,
        "color": "#f59e0b",
        "staffIds": [
            "7"
        ],
        "id": "sc-1774362703242-134"
    },
    {
        "createdAt": "2026-03-25T23:38:51.010Z",
        "name": "Ca 3",
        "date": "2026-03-25",
        "startTime": "06:00",
        "endTime": "06:30",
        "rowIdx": 2,
        "color": "#f59e0b",
        "staffIds": [
            "1774363332457",
            "1774485166775"
        ],
        "id": "sc-1774481931010-266"
    },
    {
        "createdAt": "2026-03-26T16:01:03.019Z",
        "name": "Ca 1",
        "date": "2026-03-26",
        "startTime": "06:00",
        "endTime": "13:00",
        "rowIdx": 0,
        "color": "#3b82f6",
        "staffIds": [
            "3",
            "1774363332457",
            "4"
        ],
        "id": "sc-1774515663019-286",
        "isFixed": true,
        "templateId": "tpl-row-0-1774515669445"
    },
    {
        "createdAt": "2026-03-26T16:01:09.450Z",
        "id": "shift-auto-1774515669446-0-7ehhj",
        "date": "2026-03-11",
        "startTime": "06:00",
        "endTime": "13:00",
        "rowIdx": 0,
        "isFixed": true,
        "templateId": "tpl-row-0-1774515669445",
        "staffIds": [],
        "color": "#3b82f6"
    },
    {
        "createdAt": "2026-03-26T16:01:09.450Z",
        "id": "shift-auto-1774515669446-1-mc7n9",
        "date": "2026-03-12",
        "startTime": "06:00",
        "endTime": "13:00",
        "rowIdx": 0,
        "isFixed": true,
        "templateId": "tpl-row-0-1774515669445",
        "staffIds": [],
        "color": "#3b82f6"
    },
    {
        "createdAt": "2026-03-26T16:01:09.450Z",
        "id": "shift-auto-1774515669446-2-dtxdg",
        "date": "2026-03-13",
        "startTime": "06:00",
        "endTime": "13:00",
        "rowIdx": 0,
        "isFixed": true,
        "templateId": "tpl-row-0-1774515669445",
        "staffIds": [],
        "color": "#3b82f6"
    },
    {
        "createdAt": "2026-03-26T16:01:09.450Z",
        "id": "shift-auto-1774515669446-3-wgmf4",
        "date": "2026-03-14",
        "startTime": "06:00",
        "endTime": "13:00",
        "rowIdx": 0,
        "isFixed": true,
        "templateId": "tpl-row-0-1774515669445",
        "staffIds": [],
        "color": "#3b82f6"
    },
    {
        "createdAt": "2026-03-26T16:01:09.450Z",
        "id": "shift-auto-1774515669446-4-oqie7",
        "date": "2026-03-15",
        "startTime": "06:00",
        "endTime": "13:00",
        "rowIdx": 0,
        "isFixed": true,
        "templateId": "tpl-row-0-1774515669445",
        "staffIds": [],
        "color": "#3b82f6"
    },
    {
        "createdAt": "2026-03-26T16:01:09.450Z",
        "id": "shift-auto-1774515669446-5-xlxo7",
        "date": "2026-03-16",
        "startTime": "06:00",
        "endTime": "13:00",
        "rowIdx": 0,
        "isFixed": true,
        "templateId": "tpl-row-0-1774515669445",
        "staffIds": [],
        "color": "#3b82f6"
    },
    {
        "createdAt": "2026-03-26T16:01:09.450Z",
        "id": "shift-auto-1774515669446-6-3er83",
        "date": "2026-03-17",
        "startTime": "06:00",
        "endTime": "13:00",
        "rowIdx": 0,
        "isFixed": true,
        "templateId": "tpl-row-0-1774515669445",
        "staffIds": [],
        "color": "#3b82f6"
    },
    {
        "createdAt": "2026-03-26T16:01:09.450Z",
        "id": "shift-auto-1774515669446-7-43tsb",
        "date": "2026-03-18",
        "startTime": "06:00",
        "endTime": "13:00",
        "rowIdx": 0,
        "isFixed": true,
        "templateId": "tpl-row-0-1774515669445",
        "staffIds": [],
        "color": "#3b82f6"
    },
    {
        "createdAt": "2026-03-26T16:01:09.450Z",
        "id": "shift-auto-1774515669446-8-isixs",
        "date": "2026-03-19",
        "startTime": "06:00",
        "endTime": "13:00",
        "rowIdx": 0,
        "isFixed": true,
        "templateId": "tpl-row-0-1774515669445",
        "staffIds": [],
        "color": "#3b82f6"
    },
    {
        "createdAt": "2026-03-26T16:01:09.450Z",
        "id": "shift-auto-1774515669446-9-dyqrv",
        "date": "2026-03-20",
        "startTime": "06:00",
        "endTime": "13:00",
        "rowIdx": 0,
        "isFixed": true,
        "templateId": "tpl-row-0-1774515669445",
        "staffIds": [],
        "color": "#3b82f6"
    },
    {
        "createdAt": "2026-03-26T16:01:09.450Z",
        "id": "shift-auto-1774515669446-10-rszk5",
        "date": "2026-03-21",
        "startTime": "06:00",
        "endTime": "13:00",
        "rowIdx": 0,
        "isFixed": true,
        "templateId": "tpl-row-0-1774515669445",
        "staffIds": [],
        "color": "#3b82f6"
    },
    {
        "createdAt": "2026-03-26T16:01:09.450Z",
        "id": "shift-auto-1774515669446-11-3txa5",
        "date": "2026-03-22",
        "startTime": "06:00",
        "endTime": "13:00",
        "rowIdx": 0,
        "isFixed": true,
        "templateId": "tpl-row-0-1774515669445",
        "staffIds": [],
        "color": "#3b82f6"
    },
    {
        "createdAt": "2026-03-26T16:01:09.450Z",
        "id": "shift-auto-1774515669446-12-13b4d",
        "date": "2026-03-23",
        "startTime": "06:00",
        "endTime": "13:00",
        "rowIdx": 0,
        "isFixed": true,
        "templateId": "tpl-row-0-1774515669445",
        "staffIds": [],
        "color": "#3b82f6"
    },
    {
        "createdAt": "2026-03-26T16:01:09.450Z",
        "id": "shift-auto-1774515669446-13-f8y6i",
        "date": "2026-03-24",
        "startTime": "06:00",
        "endTime": "13:00",
        "rowIdx": 0,
        "isFixed": true,
        "templateId": "tpl-row-0-1774515669445",
        "staffIds": [],
        "color": "#3b82f6"
    },
    {
        "createdAt": "2026-03-26T16:01:09.450Z",
        "id": "shift-auto-1774515669446-14-iv6t0",
        "date": "2026-03-25",
        "startTime": "06:00",
        "endTime": "13:00",
        "rowIdx": 0,
        "isFixed": true,
        "templateId": "tpl-row-0-1774515669445",
        "staffIds": [],
        "color": "#3b82f6"
    },
    {
        "createdAt": "2026-03-26T16:01:09.450Z",
        "id": "shift-auto-1774515669446-15-w19f0",
        "date": "2026-03-27",
        "startTime": "06:00",
        "endTime": "13:00",
        "rowIdx": 0,
        "isFixed": true,
        "templateId": "tpl-row-0-1774515669445",
        "staffIds": [
            "7"
        ],
        "color": "#3b82f6"
    },
    {
        "createdAt": "2026-03-26T16:01:09.450Z",
        "id": "shift-auto-1774515669446-16-02axh",
        "date": "2026-03-28",
        "startTime": "06:00",
        "endTime": "13:00",
        "rowIdx": 0,
        "isFixed": true,
        "templateId": "tpl-row-0-1774515669445",
        "staffIds": [],
        "color": "#3b82f6"
    },
    {
        "createdAt": "2026-03-26T16:01:09.450Z",
        "id": "shift-auto-1774515669446-17-tz0qh",
        "date": "2026-03-29",
        "startTime": "06:00",
        "endTime": "13:00",
        "rowIdx": 0,
        "isFixed": true,
        "templateId": "tpl-row-0-1774515669445",
        "staffIds": [],
        "color": "#3b82f6"
    },
    {
        "createdAt": "2026-03-26T16:01:09.450Z",
        "id": "shift-auto-1774515669446-18-p3csm",
        "date": "2026-03-30",
        "startTime": "06:00",
        "endTime": "13:00",
        "rowIdx": 0,
        "isFixed": true,
        "templateId": "tpl-row-0-1774515669445",
        "staffIds": [],
        "color": "#3b82f6"
    },
    {
        "createdAt": "2026-03-26T16:01:09.450Z",
        "id": "shift-auto-1774515669446-19-3699n",
        "date": "2026-03-31",
        "startTime": "06:00",
        "endTime": "13:00",
        "rowIdx": 0,
        "isFixed": true,
        "templateId": "tpl-row-0-1774515669445",
        "staffIds": [],
        "color": "#3b82f6"
    },
    {
        "createdAt": "2026-03-26T16:01:09.450Z",
        "id": "shift-auto-1774515669446-20-zd6br",
        "date": "2026-04-01",
        "startTime": "06:00",
        "endTime": "13:00",
        "rowIdx": 0,
        "isFixed": true,
        "templateId": "tpl-row-0-1774515669445",
        "staffIds": [],
        "color": "#3b82f6"
    },
    {
        "createdAt": "2026-03-26T16:01:09.450Z",
        "id": "shift-auto-1774515669446-21-0lo08",
        "date": "2026-04-02",
        "startTime": "06:00",
        "endTime": "13:00",
        "rowIdx": 0,
        "isFixed": true,
        "templateId": "tpl-row-0-1774515669445",
        "staffIds": [],
        "color": "#3b82f6"
    },
    {
        "createdAt": "2026-03-26T16:01:09.450Z",
        "id": "shift-auto-1774515669446-22-4ylhu",
        "date": "2026-04-03",
        "startTime": "06:00",
        "endTime": "13:00",
        "rowIdx": 0,
        "isFixed": true,
        "templateId": "tpl-row-0-1774515669445",
        "staffIds": [],
        "color": "#3b82f6"
    },
    {
        "createdAt": "2026-03-26T16:01:09.450Z",
        "id": "shift-auto-1774515669446-23-b87g3",
        "date": "2026-04-04",
        "startTime": "06:00",
        "endTime": "13:00",
        "rowIdx": 0,
        "isFixed": true,
        "templateId": "tpl-row-0-1774515669445",
        "staffIds": [],
        "color": "#3b82f6"
    },
    {
        "createdAt": "2026-03-26T16:01:09.450Z",
        "id": "shift-auto-1774515669446-24-bx2qq",
        "date": "2026-04-05",
        "startTime": "06:00",
        "endTime": "13:00",
        "rowIdx": 0,
        "isFixed": true,
        "templateId": "tpl-row-0-1774515669445",
        "staffIds": [],
        "color": "#3b82f6"
    },
    {
        "createdAt": "2026-03-26T16:01:09.450Z",
        "id": "shift-auto-1774515669446-25-ga8lf",
        "date": "2026-04-06",
        "startTime": "06:00",
        "endTime": "13:00",
        "rowIdx": 0,
        "isFixed": true,
        "templateId": "tpl-row-0-1774515669445",
        "staffIds": [],
        "color": "#3b82f6"
    },
    {
        "createdAt": "2026-03-26T16:01:09.450Z",
        "id": "shift-auto-1774515669446-26-ngivc",
        "date": "2026-04-07",
        "startTime": "06:00",
        "endTime": "13:00",
        "rowIdx": 0,
        "isFixed": true,
        "templateId": "tpl-row-0-1774515669445",
        "staffIds": [],
        "color": "#3b82f6"
    },
    {
        "createdAt": "2026-03-26T16:01:09.450Z",
        "id": "shift-auto-1774515669446-27-z5kbo",
        "date": "2026-04-08",
        "startTime": "06:00",
        "endTime": "13:00",
        "rowIdx": 0,
        "isFixed": true,
        "templateId": "tpl-row-0-1774515669445",
        "staffIds": [],
        "color": "#3b82f6"
    },
    {
        "createdAt": "2026-03-26T16:01:09.450Z",
        "id": "shift-auto-1774515669446-28-kpnao",
        "date": "2026-04-09",
        "startTime": "06:00",
        "endTime": "13:00",
        "rowIdx": 0,
        "isFixed": true,
        "templateId": "tpl-row-0-1774515669445",
        "staffIds": [],
        "color": "#3b82f6"
    },
    {
        "createdAt": "2026-03-26T16:01:09.450Z",
        "id": "shift-auto-1774515669446-29-rkpyu",
        "date": "2026-04-10",
        "startTime": "06:00",
        "endTime": "13:00",
        "rowIdx": 0,
        "isFixed": true,
        "templateId": "tpl-row-0-1774515669445",
        "staffIds": [],
        "color": "#3b82f6"
    },
    {
        "createdAt": "2026-03-26T16:01:09.450Z",
        "id": "shift-auto-1774515669446-30-v9c7t",
        "date": "2026-04-11",
        "startTime": "06:00",
        "endTime": "13:00",
        "rowIdx": 0,
        "isFixed": true,
        "templateId": "tpl-row-0-1774515669445",
        "staffIds": [],
        "color": "#3b82f6"
    },
    {
        "createdAt": "2026-03-26T16:01:09.450Z",
        "id": "shift-auto-1774515669446-31-5ihpr",
        "date": "2026-04-12",
        "startTime": "06:00",
        "endTime": "13:00",
        "rowIdx": 0,
        "isFixed": true,
        "templateId": "tpl-row-0-1774515669445",
        "staffIds": [],
        "color": "#3b82f6"
    },
    {
        "createdAt": "2026-03-26T16:01:09.450Z",
        "id": "shift-auto-1774515669446-32-e08ga",
        "date": "2026-04-13",
        "startTime": "06:00",
        "endTime": "13:00",
        "rowIdx": 0,
        "isFixed": true,
        "templateId": "tpl-row-0-1774515669445",
        "staffIds": [],
        "color": "#3b82f6"
    },
    {
        "createdAt": "2026-03-26T16:01:09.450Z",
        "id": "shift-auto-1774515669446-33-jiidx",
        "date": "2026-04-14",
        "startTime": "06:00",
        "endTime": "13:00",
        "rowIdx": 0,
        "isFixed": true,
        "templateId": "tpl-row-0-1774515669445",
        "staffIds": [],
        "color": "#3b82f6"
    },
    {
        "createdAt": "2026-03-26T16:01:09.450Z",
        "id": "shift-auto-1774515669446-34-3n3y1",
        "date": "2026-04-15",
        "startTime": "06:00",
        "endTime": "13:00",
        "rowIdx": 0,
        "isFixed": true,
        "templateId": "tpl-row-0-1774515669445",
        "staffIds": [],
        "color": "#3b82f6"
    },
    {
        "createdAt": "2026-03-26T16:01:09.450Z",
        "id": "shift-auto-1774515669446-35-s9e0s",
        "date": "2026-04-16",
        "startTime": "06:00",
        "endTime": "13:00",
        "rowIdx": 0,
        "isFixed": true,
        "templateId": "tpl-row-0-1774515669445",
        "staffIds": [],
        "color": "#3b82f6"
    },
    {
        "createdAt": "2026-03-26T16:01:09.450Z",
        "id": "shift-auto-1774515669446-36-bgw6y",
        "date": "2026-04-17",
        "startTime": "06:00",
        "endTime": "13:00",
        "rowIdx": 0,
        "isFixed": true,
        "templateId": "tpl-row-0-1774515669445",
        "staffIds": [],
        "color": "#3b82f6"
    },
    {
        "createdAt": "2026-03-26T16:01:09.450Z",
        "id": "shift-auto-1774515669446-37-y6p11",
        "date": "2026-04-18",
        "startTime": "06:00",
        "endTime": "13:00",
        "rowIdx": 0,
        "isFixed": true,
        "templateId": "tpl-row-0-1774515669445",
        "staffIds": [],
        "color": "#3b82f6"
    },
    {
        "createdAt": "2026-03-26T16:01:09.450Z",
        "id": "shift-auto-1774515669446-38-7fdiv",
        "date": "2026-04-19",
        "startTime": "06:00",
        "endTime": "13:00",
        "rowIdx": 0,
        "isFixed": true,
        "templateId": "tpl-row-0-1774515669445",
        "staffIds": [],
        "color": "#3b82f6"
    },
    {
        "createdAt": "2026-03-26T16:01:09.450Z",
        "id": "shift-auto-1774515669446-39-o9pyn",
        "date": "2026-04-20",
        "startTime": "06:00",
        "endTime": "13:00",
        "rowIdx": 0,
        "isFixed": true,
        "templateId": "tpl-row-0-1774515669445",
        "staffIds": [],
        "color": "#3b82f6"
    },
    {
        "createdAt": "2026-03-26T16:01:09.450Z",
        "id": "shift-auto-1774515669446-40-3i8d1",
        "date": "2026-04-21",
        "startTime": "06:00",
        "endTime": "13:00",
        "rowIdx": 0,
        "isFixed": true,
        "templateId": "tpl-row-0-1774515669445",
        "staffIds": [],
        "color": "#3b82f6"
    },
    {
        "createdAt": "2026-03-26T16:01:09.450Z",
        "id": "shift-auto-1774515669446-41-p3k4b",
        "date": "2026-04-22",
        "startTime": "06:00",
        "endTime": "13:00",
        "rowIdx": 0,
        "isFixed": true,
        "templateId": "tpl-row-0-1774515669445",
        "staffIds": [],
        "color": "#3b82f6"
    },
    {
        "createdAt": "2026-03-26T16:01:09.450Z",
        "id": "shift-auto-1774515669446-42-uydv2",
        "date": "2026-04-23",
        "startTime": "06:00",
        "endTime": "13:00",
        "rowIdx": 0,
        "isFixed": true,
        "templateId": "tpl-row-0-1774515669445",
        "staffIds": [],
        "color": "#3b82f6"
    },
    {
        "createdAt": "2026-03-26T16:01:09.450Z",
        "id": "shift-auto-1774515669446-43-h33bj",
        "date": "2026-04-24",
        "startTime": "06:00",
        "endTime": "13:00",
        "rowIdx": 0,
        "isFixed": true,
        "templateId": "tpl-row-0-1774515669445",
        "staffIds": [],
        "color": "#3b82f6"
    },
    {
        "createdAt": "2026-03-26T16:01:09.450Z",
        "id": "shift-auto-1774515669446-44-n0x2g",
        "date": "2026-04-25",
        "startTime": "06:00",
        "endTime": "13:00",
        "rowIdx": 0,
        "isFixed": true,
        "templateId": "tpl-row-0-1774515669445",
        "staffIds": [],
        "color": "#3b82f6"
    },
    {
        "createdAt": "2026-03-26T16:01:09.450Z",
        "id": "shift-auto-1774515669446-45-q4vcm",
        "date": "2026-04-26",
        "startTime": "06:00",
        "endTime": "13:00",
        "rowIdx": 0,
        "isFixed": true,
        "templateId": "tpl-row-0-1774515669445",
        "staffIds": [],
        "color": "#3b82f6"
    },
    {
        "createdAt": "2026-03-26T16:01:09.450Z",
        "id": "shift-auto-1774515669446-46-fbdrv",
        "date": "2026-04-27",
        "startTime": "06:00",
        "endTime": "13:00",
        "rowIdx": 0,
        "isFixed": true,
        "templateId": "tpl-row-0-1774515669445",
        "staffIds": [],
        "color": "#3b82f6"
    },
    {
        "createdAt": "2026-03-26T16:01:09.450Z",
        "id": "shift-auto-1774515669446-47-vp0jz",
        "date": "2026-04-28",
        "startTime": "06:00",
        "endTime": "13:00",
        "rowIdx": 0,
        "isFixed": true,
        "templateId": "tpl-row-0-1774515669445",
        "staffIds": [],
        "color": "#3b82f6"
    },
    {
        "createdAt": "2026-03-26T16:01:09.450Z",
        "id": "shift-auto-1774515669446-48-mtg1c",
        "date": "2026-04-29",
        "startTime": "06:00",
        "endTime": "13:00",
        "rowIdx": 0,
        "isFixed": true,
        "templateId": "tpl-row-0-1774515669445",
        "staffIds": [],
        "color": "#3b82f6"
    },
    {
        "createdAt": "2026-03-26T16:01:09.450Z",
        "id": "shift-auto-1774515669446-49-sjntj",
        "date": "2026-04-30",
        "startTime": "06:00",
        "endTime": "13:00",
        "rowIdx": 0,
        "isFixed": true,
        "templateId": "tpl-row-0-1774515669445",
        "staffIds": [],
        "color": "#3b82f6"
    },
    {
        "createdAt": "2026-03-26T16:01:09.450Z",
        "id": "shift-auto-1774515669446-50-60jxy",
        "date": "2026-05-01",
        "startTime": "06:00",
        "endTime": "13:00",
        "rowIdx": 0,
        "isFixed": true,
        "templateId": "tpl-row-0-1774515669445",
        "staffIds": [],
        "color": "#3b82f6"
    },
    {
        "createdAt": "2026-03-26T16:01:09.450Z",
        "id": "shift-auto-1774515669446-51-hq430",
        "date": "2026-05-02",
        "startTime": "06:00",
        "endTime": "13:00",
        "rowIdx": 0,
        "isFixed": true,
        "templateId": "tpl-row-0-1774515669445",
        "staffIds": [],
        "color": "#3b82f6"
    },
    {
        "createdAt": "2026-03-26T16:01:09.450Z",
        "id": "shift-auto-1774515669446-52-qzotv",
        "date": "2026-05-03",
        "startTime": "06:00",
        "endTime": "13:00",
        "rowIdx": 0,
        "isFixed": true,
        "templateId": "tpl-row-0-1774515669445",
        "staffIds": [],
        "color": "#3b82f6"
    },
    {
        "createdAt": "2026-03-26T16:01:09.450Z",
        "id": "shift-auto-1774515669446-53-hxpsb",
        "date": "2026-05-04",
        "startTime": "06:00",
        "endTime": "13:00",
        "rowIdx": 0,
        "isFixed": true,
        "templateId": "tpl-row-0-1774515669445",
        "staffIds": [],
        "color": "#3b82f6"
    },
    {
        "createdAt": "2026-03-26T16:01:09.450Z",
        "id": "shift-auto-1774515669446-54-wsnk5",
        "date": "2026-05-05",
        "startTime": "06:00",
        "endTime": "13:00",
        "rowIdx": 0,
        "isFixed": true,
        "templateId": "tpl-row-0-1774515669445",
        "staffIds": [],
        "color": "#3b82f6"
    },
    {
        "createdAt": "2026-03-26T16:01:09.451Z",
        "id": "shift-auto-1774515669446-55-jzzrv",
        "date": "2026-05-06",
        "startTime": "06:00",
        "endTime": "13:00",
        "rowIdx": 0,
        "isFixed": true,
        "templateId": "tpl-row-0-1774515669445",
        "staffIds": [],
        "color": "#3b82f6"
    },
    {
        "createdAt": "2026-03-26T16:01:09.451Z",
        "id": "shift-auto-1774515669446-56-fo93g",
        "date": "2026-05-07",
        "startTime": "06:00",
        "endTime": "13:00",
        "rowIdx": 0,
        "isFixed": true,
        "templateId": "tpl-row-0-1774515669445",
        "staffIds": [],
        "color": "#3b82f6"
    },
    {
        "createdAt": "2026-03-26T16:01:09.451Z",
        "id": "shift-auto-1774515669446-57-so9za",
        "date": "2026-05-08",
        "startTime": "06:00",
        "endTime": "13:00",
        "rowIdx": 0,
        "isFixed": true,
        "templateId": "tpl-row-0-1774515669445",
        "staffIds": [],
        "color": "#3b82f6"
    },
    {
        "createdAt": "2026-03-26T16:01:09.451Z",
        "id": "shift-auto-1774515669446-58-fv94f",
        "date": "2026-05-09",
        "startTime": "06:00",
        "endTime": "13:00",
        "rowIdx": 0,
        "isFixed": true,
        "templateId": "tpl-row-0-1774515669445",
        "staffIds": [],
        "color": "#3b82f6"
    },
    {
        "createdAt": "2026-03-26T16:01:09.451Z",
        "id": "shift-auto-1774515669446-59-speie",
        "date": "2026-05-10",
        "startTime": "06:00",
        "endTime": "13:00",
        "rowIdx": 0,
        "isFixed": true,
        "templateId": "tpl-row-0-1774515669445",
        "staffIds": [],
        "color": "#3b82f6"
    },
    {
        "createdAt": "2026-03-26T16:01:21.381Z",
        "name": "Ca 2",
        "date": "2026-03-26",
        "startTime": "08:30",
        "endTime": "13:15",
        "rowIdx": 1,
        "color": "#10b981",
        "staffIds": [
            "4",
            "1774485178294"
        ],
        "id": "sc-1774515681381-138",
        "isFixed": true,
        "templateId": "tpl-row-1-1774515698115"
    },
    {
        "createdAt": "2026-03-26T16:01:38.119Z",
        "id": "shift-auto-1774515698115-0-cd8le",
        "date": "2026-03-11",
        "startTime": "08:30",
        "endTime": "13:15",
        "rowIdx": 1,
        "isFixed": true,
        "templateId": "tpl-row-1-1774515698115",
        "staffIds": [],
        "color": "#10b981"
    },
    {
        "createdAt": "2026-03-26T16:01:38.119Z",
        "id": "shift-auto-1774515698115-1-etoxo",
        "date": "2026-03-12",
        "startTime": "08:30",
        "endTime": "13:15",
        "rowIdx": 1,
        "isFixed": true,
        "templateId": "tpl-row-1-1774515698115",
        "staffIds": [],
        "color": "#10b981"
    },
    {
        "createdAt": "2026-03-26T16:01:38.119Z",
        "id": "shift-auto-1774515698115-2-ux4ur",
        "date": "2026-03-13",
        "startTime": "08:30",
        "endTime": "13:15",
        "rowIdx": 1,
        "isFixed": true,
        "templateId": "tpl-row-1-1774515698115",
        "staffIds": [],
        "color": "#10b981"
    },
    {
        "createdAt": "2026-03-26T16:01:38.119Z",
        "id": "shift-auto-1774515698115-3-ay2xp",
        "date": "2026-03-14",
        "startTime": "08:30",
        "endTime": "13:15",
        "rowIdx": 1,
        "isFixed": true,
        "templateId": "tpl-row-1-1774515698115",
        "staffIds": [],
        "color": "#10b981"
    },
    {
        "createdAt": "2026-03-26T16:01:38.119Z",
        "id": "shift-auto-1774515698115-4-44ma6",
        "date": "2026-03-15",
        "startTime": "08:30",
        "endTime": "13:15",
        "rowIdx": 1,
        "isFixed": true,
        "templateId": "tpl-row-1-1774515698115",
        "staffIds": [],
        "color": "#10b981"
    },
    {
        "createdAt": "2026-03-26T16:01:38.119Z",
        "id": "shift-auto-1774515698115-5-txasi",
        "date": "2026-03-16",
        "startTime": "08:30",
        "endTime": "13:15",
        "rowIdx": 1,
        "isFixed": true,
        "templateId": "tpl-row-1-1774515698115",
        "staffIds": [],
        "color": "#10b981"
    },
    {
        "createdAt": "2026-03-26T16:01:38.119Z",
        "id": "shift-auto-1774515698115-6-tic8a",
        "date": "2026-03-17",
        "startTime": "08:30",
        "endTime": "13:15",
        "rowIdx": 1,
        "isFixed": true,
        "templateId": "tpl-row-1-1774515698115",
        "staffIds": [],
        "color": "#10b981"
    },
    {
        "createdAt": "2026-03-26T16:01:38.119Z",
        "id": "shift-auto-1774515698115-7-2fftg",
        "date": "2026-03-18",
        "startTime": "08:30",
        "endTime": "13:15",
        "rowIdx": 1,
        "isFixed": true,
        "templateId": "tpl-row-1-1774515698115",
        "staffIds": [],
        "color": "#10b981"
    },
    {
        "createdAt": "2026-03-26T16:01:38.119Z",
        "id": "shift-auto-1774515698115-8-z04al",
        "date": "2026-03-19",
        "startTime": "08:30",
        "endTime": "13:15",
        "rowIdx": 1,
        "isFixed": true,
        "templateId": "tpl-row-1-1774515698115",
        "staffIds": [],
        "color": "#10b981"
    },
    {
        "createdAt": "2026-03-26T16:01:38.119Z",
        "id": "shift-auto-1774515698115-9-1707f",
        "date": "2026-03-20",
        "startTime": "08:30",
        "endTime": "13:15",
        "rowIdx": 1,
        "isFixed": true,
        "templateId": "tpl-row-1-1774515698115",
        "staffIds": [],
        "color": "#10b981"
    },
    {
        "createdAt": "2026-03-26T16:01:38.119Z",
        "id": "shift-auto-1774515698115-10-sx4sx",
        "date": "2026-03-21",
        "startTime": "08:30",
        "endTime": "13:15",
        "rowIdx": 1,
        "isFixed": true,
        "templateId": "tpl-row-1-1774515698115",
        "staffIds": [],
        "color": "#10b981"
    },
    {
        "createdAt": "2026-03-26T16:01:38.119Z",
        "id": "shift-auto-1774515698115-11-otdza",
        "date": "2026-03-22",
        "startTime": "08:30",
        "endTime": "13:15",
        "rowIdx": 1,
        "isFixed": true,
        "templateId": "tpl-row-1-1774515698115",
        "staffIds": [],
        "color": "#10b981"
    },
    {
        "createdAt": "2026-03-26T16:01:38.119Z",
        "id": "shift-auto-1774515698115-14-h58vc",
        "date": "2026-03-25",
        "startTime": "08:30",
        "endTime": "13:15",
        "rowIdx": 1,
        "isFixed": true,
        "templateId": "tpl-row-1-1774515698115",
        "staffIds": [],
        "color": "#10b981"
    },
    {
        "createdAt": "2026-03-26T16:01:38.119Z",
        "id": "shift-auto-1774515698115-15-ldrva",
        "date": "2026-03-27",
        "startTime": "08:30",
        "endTime": "13:15",
        "rowIdx": 1,
        "isFixed": true,
        "templateId": "tpl-row-1-1774515698115",
        "staffIds": [
            "4"
        ],
        "color": "#10b981"
    },
    {
        "createdAt": "2026-03-26T16:01:38.119Z",
        "id": "shift-auto-1774515698115-16-shczd",
        "date": "2026-03-28",
        "startTime": "08:30",
        "endTime": "13:15",
        "rowIdx": 1,
        "isFixed": true,
        "templateId": "tpl-row-1-1774515698115",
        "staffIds": [],
        "color": "#10b981"
    },
    {
        "createdAt": "2026-03-26T16:01:38.119Z",
        "id": "shift-auto-1774515698115-17-47xph",
        "date": "2026-03-29",
        "startTime": "08:30",
        "endTime": "13:15",
        "rowIdx": 1,
        "isFixed": true,
        "templateId": "tpl-row-1-1774515698115",
        "staffIds": [],
        "color": "#10b981"
    },
    {
        "createdAt": "2026-03-26T16:01:38.119Z",
        "id": "shift-auto-1774515698115-18-531oj",
        "date": "2026-03-30",
        "startTime": "08:30",
        "endTime": "13:15",
        "rowIdx": 1,
        "isFixed": true,
        "templateId": "tpl-row-1-1774515698115",
        "staffIds": [],
        "color": "#10b981"
    },
    {
        "createdAt": "2026-03-26T16:01:38.119Z",
        "id": "shift-auto-1774515698115-19-psgep",
        "date": "2026-03-31",
        "startTime": "08:30",
        "endTime": "13:15",
        "rowIdx": 1,
        "isFixed": true,
        "templateId": "tpl-row-1-1774515698115",
        "staffIds": [],
        "color": "#10b981"
    },
    {
        "createdAt": "2026-03-26T16:01:38.119Z",
        "id": "shift-auto-1774515698115-20-8pyla",
        "date": "2026-04-01",
        "startTime": "08:30",
        "endTime": "13:15",
        "rowIdx": 1,
        "isFixed": true,
        "templateId": "tpl-row-1-1774515698115",
        "staffIds": [],
        "color": "#10b981"
    },
    {
        "createdAt": "2026-03-26T16:01:38.119Z",
        "id": "shift-auto-1774515698115-21-17qnu",
        "date": "2026-04-02",
        "startTime": "08:30",
        "endTime": "13:15",
        "rowIdx": 1,
        "isFixed": true,
        "templateId": "tpl-row-1-1774515698115",
        "staffIds": [],
        "color": "#10b981"
    },
    {
        "createdAt": "2026-03-26T16:01:38.119Z",
        "id": "shift-auto-1774515698115-22-755ht",
        "date": "2026-04-03",
        "startTime": "08:30",
        "endTime": "13:15",
        "rowIdx": 1,
        "isFixed": true,
        "templateId": "tpl-row-1-1774515698115",
        "staffIds": [],
        "color": "#10b981"
    },
    {
        "createdAt": "2026-03-26T16:01:38.119Z",
        "id": "shift-auto-1774515698115-23-6k5he",
        "date": "2026-04-04",
        "startTime": "08:30",
        "endTime": "13:15",
        "rowIdx": 1,
        "isFixed": true,
        "templateId": "tpl-row-1-1774515698115",
        "staffIds": [],
        "color": "#10b981"
    },
    {
        "createdAt": "2026-03-26T16:01:38.119Z",
        "id": "shift-auto-1774515698115-24-ybnjo",
        "date": "2026-04-05",
        "startTime": "08:30",
        "endTime": "13:15",
        "rowIdx": 1,
        "isFixed": true,
        "templateId": "tpl-row-1-1774515698115",
        "staffIds": [],
        "color": "#10b981"
    },
    {
        "createdAt": "2026-03-26T16:01:38.119Z",
        "id": "shift-auto-1774515698115-25-t1858",
        "date": "2026-04-06",
        "startTime": "08:30",
        "endTime": "13:15",
        "rowIdx": 1,
        "isFixed": true,
        "templateId": "tpl-row-1-1774515698115",
        "staffIds": [],
        "color": "#10b981"
    },
    {
        "createdAt": "2026-03-26T16:01:38.119Z",
        "id": "shift-auto-1774515698115-26-fkrl6",
        "date": "2026-04-07",
        "startTime": "08:30",
        "endTime": "13:15",
        "rowIdx": 1,
        "isFixed": true,
        "templateId": "tpl-row-1-1774515698115",
        "staffIds": [],
        "color": "#10b981"
    },
    {
        "createdAt": "2026-03-26T16:01:38.119Z",
        "id": "shift-auto-1774515698115-27-koc3o",
        "date": "2026-04-08",
        "startTime": "08:30",
        "endTime": "13:15",
        "rowIdx": 1,
        "isFixed": true,
        "templateId": "tpl-row-1-1774515698115",
        "staffIds": [],
        "color": "#10b981"
    },
    {
        "createdAt": "2026-03-26T16:01:38.119Z",
        "id": "shift-auto-1774515698115-28-m1cpy",
        "date": "2026-04-09",
        "startTime": "08:30",
        "endTime": "13:15",
        "rowIdx": 1,
        "isFixed": true,
        "templateId": "tpl-row-1-1774515698115",
        "staffIds": [],
        "color": "#10b981"
    },
    {
        "createdAt": "2026-03-26T16:01:38.119Z",
        "id": "shift-auto-1774515698115-29-gkluc",
        "date": "2026-04-10",
        "startTime": "08:30",
        "endTime": "13:15",
        "rowIdx": 1,
        "isFixed": true,
        "templateId": "tpl-row-1-1774515698115",
        "staffIds": [],
        "color": "#10b981"
    },
    {
        "createdAt": "2026-03-26T16:01:38.119Z",
        "id": "shift-auto-1774515698115-30-6u0z5",
        "date": "2026-04-11",
        "startTime": "08:30",
        "endTime": "13:15",
        "rowIdx": 1,
        "isFixed": true,
        "templateId": "tpl-row-1-1774515698115",
        "staffIds": [],
        "color": "#10b981"
    },
    {
        "createdAt": "2026-03-26T16:01:38.119Z",
        "id": "shift-auto-1774515698115-31-knilb",
        "date": "2026-04-12",
        "startTime": "08:30",
        "endTime": "13:15",
        "rowIdx": 1,
        "isFixed": true,
        "templateId": "tpl-row-1-1774515698115",
        "staffIds": [],
        "color": "#10b981"
    },
    {
        "createdAt": "2026-03-26T16:01:38.119Z",
        "id": "shift-auto-1774515698115-32-z7c7p",
        "date": "2026-04-13",
        "startTime": "08:30",
        "endTime": "13:15",
        "rowIdx": 1,
        "isFixed": true,
        "templateId": "tpl-row-1-1774515698115",
        "staffIds": [],
        "color": "#10b981"
    },
    {
        "createdAt": "2026-03-26T16:01:38.119Z",
        "id": "shift-auto-1774515698115-33-nkhvt",
        "date": "2026-04-14",
        "startTime": "08:30",
        "endTime": "13:15",
        "rowIdx": 1,
        "isFixed": true,
        "templateId": "tpl-row-1-1774515698115",
        "staffIds": [],
        "color": "#10b981"
    },
    {
        "createdAt": "2026-03-26T16:01:38.119Z",
        "id": "shift-auto-1774515698115-34-939ii",
        "date": "2026-04-15",
        "startTime": "08:30",
        "endTime": "13:15",
        "rowIdx": 1,
        "isFixed": true,
        "templateId": "tpl-row-1-1774515698115",
        "staffIds": [],
        "color": "#10b981"
    },
    {
        "createdAt": "2026-03-26T16:01:38.119Z",
        "id": "shift-auto-1774515698115-35-1vq7w",
        "date": "2026-04-16",
        "startTime": "08:30",
        "endTime": "13:15",
        "rowIdx": 1,
        "isFixed": true,
        "templateId": "tpl-row-1-1774515698115",
        "staffIds": [],
        "color": "#10b981"
    },
    {
        "createdAt": "2026-03-26T16:01:38.119Z",
        "id": "shift-auto-1774515698115-36-j3oqn",
        "date": "2026-04-17",
        "startTime": "08:30",
        "endTime": "13:15",
        "rowIdx": 1,
        "isFixed": true,
        "templateId": "tpl-row-1-1774515698115",
        "staffIds": [],
        "color": "#10b981"
    },
    {
        "createdAt": "2026-03-26T16:01:38.119Z",
        "id": "shift-auto-1774515698115-37-02x3j",
        "date": "2026-04-18",
        "startTime": "08:30",
        "endTime": "13:15",
        "rowIdx": 1,
        "isFixed": true,
        "templateId": "tpl-row-1-1774515698115",
        "staffIds": [],
        "color": "#10b981"
    },
    {
        "createdAt": "2026-03-26T16:01:38.119Z",
        "id": "shift-auto-1774515698115-38-w6obd",
        "date": "2026-04-19",
        "startTime": "08:30",
        "endTime": "13:15",
        "rowIdx": 1,
        "isFixed": true,
        "templateId": "tpl-row-1-1774515698115",
        "staffIds": [],
        "color": "#10b981"
    },
    {
        "createdAt": "2026-03-26T16:01:38.119Z",
        "id": "shift-auto-1774515698115-39-jx41a",
        "date": "2026-04-20",
        "startTime": "08:30",
        "endTime": "13:15",
        "rowIdx": 1,
        "isFixed": true,
        "templateId": "tpl-row-1-1774515698115",
        "staffIds": [],
        "color": "#10b981"
    },
    {
        "createdAt": "2026-03-26T16:01:38.119Z",
        "id": "shift-auto-1774515698115-40-8nyyq",
        "date": "2026-04-21",
        "startTime": "08:30",
        "endTime": "13:15",
        "rowIdx": 1,
        "isFixed": true,
        "templateId": "tpl-row-1-1774515698115",
        "staffIds": [],
        "color": "#10b981"
    },
    {
        "createdAt": "2026-03-26T16:01:38.119Z",
        "id": "shift-auto-1774515698115-41-m23qr",
        "date": "2026-04-22",
        "startTime": "08:30",
        "endTime": "13:15",
        "rowIdx": 1,
        "isFixed": true,
        "templateId": "tpl-row-1-1774515698115",
        "staffIds": [],
        "color": "#10b981"
    },
    {
        "createdAt": "2026-03-26T16:01:38.119Z",
        "id": "shift-auto-1774515698115-42-gff0e",
        "date": "2026-04-23",
        "startTime": "08:30",
        "endTime": "13:15",
        "rowIdx": 1,
        "isFixed": true,
        "templateId": "tpl-row-1-1774515698115",
        "staffIds": [],
        "color": "#10b981"
    },
    {
        "createdAt": "2026-03-26T16:01:38.119Z",
        "id": "shift-auto-1774515698115-43-epa5s",
        "date": "2026-04-24",
        "startTime": "08:30",
        "endTime": "13:15",
        "rowIdx": 1,
        "isFixed": true,
        "templateId": "tpl-row-1-1774515698115",
        "staffIds": [],
        "color": "#10b981"
    },
    {
        "createdAt": "2026-03-26T16:01:38.119Z",
        "id": "shift-auto-1774515698115-44-vawef",
        "date": "2026-04-25",
        "startTime": "08:30",
        "endTime": "13:15",
        "rowIdx": 1,
        "isFixed": true,
        "templateId": "tpl-row-1-1774515698115",
        "staffIds": [],
        "color": "#10b981"
    },
    {
        "createdAt": "2026-03-26T16:01:38.119Z",
        "id": "shift-auto-1774515698115-45-bxovg",
        "date": "2026-04-26",
        "startTime": "08:30",
        "endTime": "13:15",
        "rowIdx": 1,
        "isFixed": true,
        "templateId": "tpl-row-1-1774515698115",
        "staffIds": [],
        "color": "#10b981"
    },
    {
        "createdAt": "2026-03-26T16:01:38.119Z",
        "id": "shift-auto-1774515698115-46-ib357",
        "date": "2026-04-27",
        "startTime": "08:30",
        "endTime": "13:15",
        "rowIdx": 1,
        "isFixed": true,
        "templateId": "tpl-row-1-1774515698115",
        "staffIds": [],
        "color": "#10b981"
    },
    {
        "createdAt": "2026-03-26T16:01:38.119Z",
        "id": "shift-auto-1774515698115-47-ix7go",
        "date": "2026-04-28",
        "startTime": "08:30",
        "endTime": "13:15",
        "rowIdx": 1,
        "isFixed": true,
        "templateId": "tpl-row-1-1774515698115",
        "staffIds": [],
        "color": "#10b981"
    },
    {
        "createdAt": "2026-03-26T16:01:38.119Z",
        "id": "shift-auto-1774515698115-48-rqczk",
        "date": "2026-04-29",
        "startTime": "08:30",
        "endTime": "13:15",
        "rowIdx": 1,
        "isFixed": true,
        "templateId": "tpl-row-1-1774515698115",
        "staffIds": [],
        "color": "#10b981"
    },
    {
        "createdAt": "2026-03-26T16:01:38.119Z",
        "id": "shift-auto-1774515698115-49-4mzq0",
        "date": "2026-04-30",
        "startTime": "08:30",
        "endTime": "13:15",
        "rowIdx": 1,
        "isFixed": true,
        "templateId": "tpl-row-1-1774515698115",
        "staffIds": [],
        "color": "#10b981"
    },
    {
        "createdAt": "2026-03-26T16:01:38.119Z",
        "id": "shift-auto-1774515698115-50-srby1",
        "date": "2026-05-01",
        "startTime": "08:30",
        "endTime": "13:15",
        "rowIdx": 1,
        "isFixed": true,
        "templateId": "tpl-row-1-1774515698115",
        "staffIds": [],
        "color": "#10b981"
    },
    {
        "createdAt": "2026-03-26T16:01:38.119Z",
        "id": "shift-auto-1774515698115-51-vx80v",
        "date": "2026-05-02",
        "startTime": "08:30",
        "endTime": "13:15",
        "rowIdx": 1,
        "isFixed": true,
        "templateId": "tpl-row-1-1774515698115",
        "staffIds": [],
        "color": "#10b981"
    },
    {
        "createdAt": "2026-03-26T16:01:38.119Z",
        "id": "shift-auto-1774515698115-52-ugg1l",
        "date": "2026-05-03",
        "startTime": "08:30",
        "endTime": "13:15",
        "rowIdx": 1,
        "isFixed": true,
        "templateId": "tpl-row-1-1774515698115",
        "staffIds": [],
        "color": "#10b981"
    },
    {
        "createdAt": "2026-03-26T16:01:38.119Z",
        "id": "shift-auto-1774515698115-53-y02g1",
        "date": "2026-05-04",
        "startTime": "08:30",
        "endTime": "13:15",
        "rowIdx": 1,
        "isFixed": true,
        "templateId": "tpl-row-1-1774515698115",
        "staffIds": [],
        "color": "#10b981"
    },
    {
        "createdAt": "2026-03-26T16:01:38.119Z",
        "id": "shift-auto-1774515698115-54-jdcd8",
        "date": "2026-05-05",
        "startTime": "08:30",
        "endTime": "13:15",
        "rowIdx": 1,
        "isFixed": true,
        "templateId": "tpl-row-1-1774515698115",
        "staffIds": [],
        "color": "#10b981"
    },
    {
        "createdAt": "2026-03-26T16:01:38.119Z",
        "id": "shift-auto-1774515698115-55-1z0np",
        "date": "2026-05-06",
        "startTime": "08:30",
        "endTime": "13:15",
        "rowIdx": 1,
        "isFixed": true,
        "templateId": "tpl-row-1-1774515698115",
        "staffIds": [],
        "color": "#10b981"
    },
    {
        "createdAt": "2026-03-26T16:01:38.119Z",
        "id": "shift-auto-1774515698115-56-c58pr",
        "date": "2026-05-07",
        "startTime": "08:30",
        "endTime": "13:15",
        "rowIdx": 1,
        "isFixed": true,
        "templateId": "tpl-row-1-1774515698115",
        "staffIds": [],
        "color": "#10b981"
    },
    {
        "createdAt": "2026-03-26T16:01:38.119Z",
        "id": "shift-auto-1774515698115-57-rmag3",
        "date": "2026-05-08",
        "startTime": "08:30",
        "endTime": "13:15",
        "rowIdx": 1,
        "isFixed": true,
        "templateId": "tpl-row-1-1774515698115",
        "staffIds": [],
        "color": "#10b981"
    },
    {
        "createdAt": "2026-03-26T16:01:38.119Z",
        "id": "shift-auto-1774515698115-58-grosm",
        "date": "2026-05-09",
        "startTime": "08:30",
        "endTime": "13:15",
        "rowIdx": 1,
        "isFixed": true,
        "templateId": "tpl-row-1-1774515698115",
        "staffIds": [],
        "color": "#10b981"
    },
    {
        "createdAt": "2026-03-26T16:01:38.119Z",
        "id": "shift-auto-1774515698115-59-05aa2",
        "date": "2026-05-10",
        "startTime": "08:30",
        "endTime": "13:15",
        "rowIdx": 1,
        "isFixed": true,
        "templateId": "tpl-row-1-1774515698115",
        "staffIds": [],
        "color": "#10b981"
    },
    {
        "createdAt": "2026-03-26T16:01:50.806Z",
        "name": "Ca 3",
        "date": "2026-03-26",
        "startTime": "08:00",
        "endTime": "12:00",
        "rowIdx": 2,
        "color": "#f59e0b",
        "staffIds": [
            "7"
        ],
        "id": "sc-1774515710806-923",
        "isFixed": false
    },
    {
        "createdAt": "2026-03-26T16:02:06.897Z",
        "name": "Ca 4",
        "date": "2026-03-26",
        "startTime": "12:00",
        "endTime": "13:00",
        "rowIdx": 3,
        "color": "#8b5cf6",
        "staffIds": [
            "1774485166775"
        ],
        "id": "sc-1774515726897-191",
        "isFixed": false
    },
    {
        "createdAt": "2026-03-26T16:34:44.372Z",
        "id": "shift-auto-1774517684366-0-6xn16",
        "date": "2026-03-23",
        "startTime": "08:30",
        "endTime": "13:15",
        "rowIdx": 1,
        "isFixed": true,
        "templateId": "tpl-row-1-1774515698115",
        "staffIds": [],
        "color": "#10b981"
    },
    {
        "createdAt": "2026-03-26T16:34:44.372Z",
        "id": "shift-auto-1774517684366-1-574dm",
        "date": "2026-03-24",
        "startTime": "08:30",
        "endTime": "13:15",
        "rowIdx": 1,
        "isFixed": true,
        "templateId": "tpl-row-1-1774515698115",
        "staffIds": [],
        "color": "#10b981"
    }
]